python_qualify/__init__.py
python_qualify/api.py
python_qualify/clone.py
python_qualify/finder.py
python_qualify/loader.py
python_qualify/logging.py
python_qualify/settings.py
python_qualify/version.py
python_qualify-0.1.1.dist-info/LICENSE
python_qualify-0.1.1.dist-info/METADATA
python_qualify-0.1.1.dist-info/WHEEL
python_qualify-0.1.1.dist-info/RECORD
