Metadata-Version: 2.1
Name: python-qualify
Version: 0.1.1
Summary: Import top-level modules from a directory not on `sys.path`
License: Apache-2.0
Author: Claudia Pellegrino
Author-email: clau@tiqua.de
Requires-Python: >=3.8
Classifier: Development Status :: 3 - Alpha
Classifier: License :: OSI Approved :: Apache Software License
Classifier: Programming Language :: Python :: 3
Classifier: Programming Language :: Python :: 3.8
Classifier: Programming Language :: Python :: 3.9
Classifier: Programming Language :: Python :: 3.10
Classifier: Programming Language :: Python :: 3.11
Classifier: Programming Language :: Python :: 3.12
Classifier: Topic :: Software Development :: Libraries :: Python Modules
Classifier: Typing :: Typed
Requires-Dist: colorama
Requires-Dist: fire
Requires-Dist: wrapt (>=1.16.0,<2.0.0)
